LICENSE
README.md
setup.cfg
setup.py
src/yookassa/__init__.py
src/yookassa/client.py
src/yookassa/configuration.py
src/yookassa/deal.py
src/yookassa/invoice.py
src/yookassa/payment.py
src/yookassa/payment_method.py
src/yookassa/payout.py
src/yookassa/personal_data.py
src/yookassa/receipt.py
src/yookassa/refund.py
src/yookassa/sbp_banks.py
src/yookassa/self_employed.py
src/yookassa/settings.py
src/yookassa/webhook.py
src/yookassa.egg-info/PKG-INFO
src/yookassa.egg-info/SOURCES.txt
src/yookassa.egg-info/dependency_links.txt
src/yookassa.egg-info/not-zip-safe
src/yookassa.egg-info/requires.txt
src/yookassa.egg-info/top_level.txt
src/yookassa/domain/__init__.py
src/yookassa/domain/common/__init__.py
src/yookassa/domain/common/base_object.py
src/yookassa/domain/common/confirmation_type.py
src/yookassa/domain/common/context.py
src/yookassa/domain/common/data_context.py
src/yookassa/domain/common/http_verb.py
src/yookassa/domain/common/locale.py
src/yookassa/domain/common/payment_method_type.py
src/yookassa/domain/common/receipt_type.py
src/yookassa/domain/common/request_object.py
src/yookassa/domain/common/response_object.py
src/yookassa/domain/common/security_helper.py
src/yookassa/domain/common/type_factory.py
src/yookassa/domain/common/user_agent.py
src/yookassa/domain/errors/__init__.py
src/yookassa/domain/errors/error.py
src/yookassa/domain/errors/error_code.py
src/yookassa/domain/exceptions/__init__.py
src/yookassa/domain/exceptions/api_error.py
src/yookassa/domain/exceptions/bad_request_error.py
src/yookassa/domain/exceptions/forbidden_error.py
src/yookassa/domain/exceptions/gone_error.py
src/yookassa/domain/exceptions/internal_server_error.py
src/yookassa/domain/exceptions/not_found_error.py
src/yookassa/domain/exceptions/response_processing_error.py
src/yookassa/domain/exceptions/too_many_request_error.py
src/yookassa/domain/exceptions/unauthorized_error.py
src/yookassa/domain/helpers/__init__.py
src/yookassa/domain/helpers/product_code.py
src/yookassa/domain/models/__init__.py
src/yookassa/domain/models/amount.py
src/yookassa/domain/models/cancellation_details.py
src/yookassa/domain/models/currency.py
src/yookassa/domain/models/deal.py
