Metadata-Version: 2.4
Name: yookassa
Version: 3.7.0
Summary: YooKassa API SDK Python Library
Home-page: https://git.yoomoney.ru/projects/SDK/repos/yookassa-sdk-python
Author: YooMoney
Author-email: cms@yoomoney.ru
License: MIT
Keywords: yoomoney,yookassa,payout,sdk,python
Classifier: License :: OSI Approved :: MIT License
Classifier: Programming Language :: Python
Classifier: Programming Language :: Python :: 3
Classifier: Programming Language :: Python :: 3.7
Classifier: Programming Language :: Python :: 3.8
Classifier: Programming Language :: Python :: 3.9
Classifier: Programming Language :: Python :: 3.10
Classifier: Programming Language :: Python :: 3.11
Classifier: Programming Language :: Python :: 3.12
Classifier: Programming Language :: Python :: 3 :: Only
License-File: LICENSE
Requires-Dist: requests
Requires-Dist: urllib3
Requires-Dist: netaddr
Requires-Dist: distro
Requires-Dist: deprecated
Dynamic: author
Dynamic: author-email
Dynamic: classifier
Dynamic: description
Dynamic: description-content-type
Dynamic: home-page
Dynamic: keywords
Dynamic: license
Dynamic: license-file
Dynamic: requires-dist
Dynamic: summary
